ConstitutionUz/ConstitutionUz.py
ConstitutionUz/__init__.py
ConstitutionUz/py.typed
ConstitutionUz-1.0.1.dist-info/METADATA
ConstitutionUz-1.0.1.dist-info/WHEEL
ConstitutionUz-1.0.1.dist-info/top_level.txt
ConstitutionUz-1.0.1.dist-info/RECORD
